Asynchronous_FIFO/design.v
module async_fifo #(
    parameter DATA_WIDTH = 8,
    parameter ADDR_WIDTH = 4
)(
    input  wire                 wr_clk,
    input  wire                 wr_rst,
    input  wire                 wr_en,
    input  wire [DATA_WIDTH-1:0] wr_data,
    output wire                 full,

    input  wire                 rd_clk,
    input  wire                 rd_rst,
    input  wire                 rd_en,
    output wire [DATA_WIDTH-1:0] rd_data,
    output wire                 empty
);

    localparam DEPTH = 1 << ADDR_WIDTH;

    reg [DATA_WIDTH-1:0] mem [0:DEPTH-1];

    reg [ADDR_WIDTH:0] wr_ptr_bin, wr_ptr_gray, wr_ptr_gray_sync1, wr_ptr_gray_sync2;
    reg [ADDR_WIDTH:0] rd_ptr_bin, rd_ptr_gray, rd_ptr_gray_sync1, rd_ptr_gray_sync2;

    always @(posedge wr_clk or posedge wr_rst) begin
        if (wr_rst) begin
            wr_ptr_bin <= 0;
            wr_ptr_gray <= 0;
        end else if (wr_en && !full) begin
            mem[wr_ptr_bin[ADDR_WIDTH-1:0]] <= wr_data;
            wr_ptr_bin <= wr_ptr_bin + 1;
            wr_ptr_gray <= (wr_ptr_bin + 1) ^ ((wr_ptr_bin + 1) >> 1);
        end
    end

    always @(posedge rd_clk or posedge rd_rst) begin
        if (rd_rst) begin
            rd_ptr_bin <= 0;
            rd_ptr_gray <= 0;
        end else if (rd_en && !empty) begin
            rd_ptr_bin <= rd_ptr_bin + 1;
            rd_ptr_gray <= (rd_ptr_bin + 1) ^ ((rd_ptr_bin + 1) >> 1);
        end
    end

    assign rd_data = mem[rd_ptr_bin[ADDR_WIDTH-1:0]];

    always @(posedge wr_clk) begin
        rd_ptr_gray_sync1 <= rd_ptr_gray;
        rd_ptr_gray_sync2 <= rd_ptr_gray_sync1;
    end

    always @(posedge rd_clk) begin
        wr_ptr_gray_sync1 <= wr_ptr_gray;
        wr_ptr_gray_sync2 <= wr_ptr_gray_sync1;
    end

    function [ADDR_WIDTH:0] gray_to_bin;
        input [ADDR_WIDTH:0] gray;
        integer i;
        begin
            gray_to_bin[ADDR_WIDTH] = gray[ADDR_WIDTH];
            for (i = ADDR_WIDTH-1; i >= 0; i = i - 1)
                gray_to_bin[i] = gray_to_bin[i+1] ^ gray[i];
        end
    endfunction

    wire [ADDR_WIDTH:0] wr_ptr_bin_sync = gray_to_bin(rd_ptr_gray_sync2);
    wire [ADDR_WIDTH:0] rd_ptr_bin_sync = gray_to_bin(wr_ptr_gray_sync2);

    assign full  = (wr_ptr_gray == {~rd_ptr_gray_sync2[ADDR_WIDTH:ADDR_WIDTH-1], rd_ptr_gray_sync2[ADDR_WIDTH-2:0]});
    assign empty = (rd_ptr_gray == wr_ptr_gray_sync2);

endmodule

Asynchronous_FIFO/testbench.v
`timescale 1ns/1ps
`include"design.v"
module async_fifo_tb;

    parameter DATA_WIDTH = 8;
    parameter ADDR_WIDTH = 4;

    reg wr_clk, rd_clk;
    reg wr_rst, rd_rst;
    reg wr_en, rd_en;
    reg [DATA_WIDTH-1:0] wr_data;
    wire [DATA_WIDTH-1:0] rd_data;
    wire full, empty;

    async_fifo #(
        .DATA_WIDTH(DATA_WIDTH),
        .ADDR_WIDTH(ADDR_WIDTH)
    ) uut (
        .wr_clk(wr_clk),
        .wr_rst(wr_rst),
        .wr_en(wr_en),
        .wr_data(wr_data),
        .full(full),
        .rd_clk(rd_clk),
        .rd_rst(rd_rst),
        .rd_en(rd_en),
        .rd_data(rd_data),
        .empty(empty)
    );

    initial begin
        wr_clk = 0;
        rd_clk = 0;
        forever #5 wr_clk = ~wr_clk;
    end

    initial begin
        forever #7 rd_clk = ~rd_clk;
    end

    initial begin
        wr_rst = 1;
        rd_rst = 1;
        wr_en = 0;
        rd_en = 0;
        wr_data = 0;

        #20;
        wr_rst = 0;
        rd_rst = 0;

        #10;

        // Write data into FIFO
        repeat (10) begin
            @(posedge wr_clk);
            if (!full) begin
                wr_en = 1;
                wr_data = wr_data + 1;
            end else begin
                wr_en = 0;
            end
        end
        wr_en = 0;

        #50;

        // Read data from FIFO
        repeat (10) begin
            @(posedge rd_clk);
            if (!empty) begin
                rd_en = 1;
            end else begin
                rd_en = 0;
            end
        end
        rd_en = 0;

        #100;
        $finish;
    end

initial begin
    $dumpfile("dump.vcd"); 
    $dumpvars(0, async_fifo_tb);  
end

endmodule

Asynchronous_FIFO/dump.vcd
$date
	Fri May  2 18:18:17 2025
$end
$version
	Icarus Verilog
$end
$timescale
	1ps
$end
$scope module async_fifo_tb $end
$var wire 8 ! rd_data [7:0] $end
$var wire 1 " full $end
$var wire 1 # empty $end
$var parameter 32 $ ADDR_WIDTH $end
$var parameter 32 % DATA_WIDTH $end
$var reg 1 & rd_clk $end
$var reg 1 ' rd_en $end
$var reg 1 ( rd_rst $end
$var reg 1 ) wr_clk $end
$var reg 8 * wr_data [7:0] $end
$var reg 1 + wr_en $end
$var reg 1 , wr_rst $end
$scope module uut $end
$var wire 1 & rd_clk $end
$var wire 8 - rd_data [7:0] $end
$var wire 1 ' rd_en $end
$var wire 1 ( rd_rst $end
$var wire 1 ) wr_clk $end
$var wire 8 . wr_data [7:0] $end
$var wire 1 + wr_en $end
$var wire 1 , wr_rst $end
$var wire 5 / wr_ptr_bin_sync [4:0] $end
$var wire 5 0 rd_ptr_bin_sync [4:0] $end
$var wire 1 " full $end
$var wire 1 # empty $end
$var parameter 32 1 ADDR_WIDTH $end
$var parameter 32 2 DATA_WIDTH $end
$var parameter 36 3 DEPTH $end
$var reg 5 4 rd_ptr_bin [4:0] $end
$var reg 5 5 rd_ptr_gray [4:0] $end
$var reg 5 6 rd_ptr_gray_sync1 [4:0] $end
$var reg 5 7 rd_ptr_gray_sync2 [4:0] $end
$var reg 5 8 wr_ptr_bin [4:0] $end
$var reg 5 9 wr_ptr_gray [4:0] $end
$var reg 5 : wr_ptr_gray_sync1 [4:0] $end
$var reg 5 ; wr_ptr_gray_sync2 [4:0] $end
$scope function gray_to_bin $end
$var reg 5 < gray [4:0] $end
$var integer 32 = i [31:0] $end
$upscope $end
$upscope $end
$upscope $end
$enddefinitions $end
$comment Show the parameter values. $end
$dumpall
b10000 3
b1000 2
b100 1
b1000 %
b100 $
$end
#0
$dumpvars
b11111111111111111111111111111111 =
bx <
bx ;
bx :
b0 9
b0 8
bx 7
bx 6
b0 5
b0 4
bx 0
bx /
b0 .
bx -
1,
0+
b0 *
0)
1(
0'
0&
x#
x"
bx !
$end
#5000
b0 6
1)
#7000
b0 :
1&
#10000
0)
#14000
0&
#15000
0"
b0 /
b11111111111111111111111111111111 =
b0 <
b0 7
1)
#20000
0)
0(
0,
#21000
b0 0
b11111111111111111111111111111111 =
1#
b0 ;
1&
#25000
1)
#28000
0&
#30000
0)
#35000
b1 *
b1 .
1+
1)
1&
#40000
0)
#42000
0&
#45000
b1 9
b1 8
b1 !
b1 -
b10 *
b10 .
1)
#49000
b1 :
1&
#50000
0)
#55000
b11 9
b10 8
b11 *
b11 .
1)
#56000
0&
#60000
0)
#63000
b1 0
b11111111111111111111111111111111 =
b1 <
0#
b1 ;
b11 :
1&
#65000
b10 9
b11 8
b100 *
b100 .
1)
#70000
0)
0&
#75000
b110 9
b100 8
b101 *
b101 .
1)
#77000
b10 0
b11111111111111111111111111111111 =
b11 <
b11 ;
b110 :
1&
#80000
0)
#84000
0&
#85000
b111 9
b101 8
b110 *
b110 .
1)
#90000
0)
#91000
b100 0
b11111111111111111111111111111111 =
b110 <
b110 ;
b111 :
1&
#95000
b101 9
b110 8
b111 *
b111 .
1)
#98000
0&
#100000
0)
#105000
b101 0
b11111111111111111111111111111111 =
b111 <
b100 9
b111 8
b111 ;
b101 :
b1000 *
b1000 .
1)
1&
#110000
0)
#112000
0&
#115000
b1100 9
b1000 8
b1001 *
b1001 .
1)
#119000
b110 0
b11111111111111111111111111111111 =
b101 <
b101 ;
b1100 :
1&
#120000
0)
#125000
b1101 9
b1001 8
0+
b1010 *
b1010 .
1)
#126000
0&
#130000
0)
#133000
b1000 0
b11111111111111111111111111111111 =
b1100 <
b1100 ;
b1101 :
1&
#135000
1)
#140000
0)
0&
#145000
1)
#147000
b1001 0
b11111111111111111111111111111111 =
b1101 <
b1101 ;
1&
#150000
0)
#154000
0&
#155000
1)
#160000
0)
#161000
1&
#165000
1)
#168000
0&
#170000
0)
#175000
1'
1)
1&
#180000
0)
#182000
0&
#185000
1)
#189000
b10 !
b10 -
b1 5
b1 4
1&
#190000
0)
#195000
b1 6
1)
#196000
0&
#200000
0)
#203000
b11 !
b11 -
b11 5
b10 4
1&
#205000
b1 /
b11111111111111111111111111111111 =
b1 <
b1 7
b11 6
1)
#210000
0)
0&
#215000
b10 /
b11111111111111111111111111111111 =
b11 <
b11 7
1)
#217000
b100 !
b100 -
b10 5
b11 4
1&
#220000
0)
#224000
0&
#225000
b10 6
1)
#230000
0)
#231000
b101 !
b101 -
b110 5
b100 4
1&
#235000
b11 /
b11111111111111111111111111111111 =
b10 <
b10 7
b110 6
1)
#238000
0&
#240000
0)
#245000
b100 /
b11111111111111111111111111111111 =
b110 <
b110 !
b110 -
b110 7
b111 5
b101 4
1)
1&
#250000
0)
#252000
0&
#255000
b111 6
1)
#259000
b111 !
b111 -
b101 5
b110 4
1&
#260000
0)
#265000
b101 /
b11111111111111111111111111111111 =
b111 <
b111 7
b101 6
1)
#266000
0&
#270000
0)
#273000
b1000 !
b1000 -
b100 5
b111 4
1&
#275000
b110 /
b11111111111111111111111111111111 =
b101 <
b101 7
b100 6
1)
#280000
0)
0&
#285000
b111 /
b11111111111111111111111111111111 =
b100 <
b100 7
1)
#287000
b1001 !
b1001 -
b1100 5
b1000 4
1&
#290000
0)
#294000
0&
#295000
b1100 6
1)
#300000
0)
#301000
bx !
bx -
1#
b1101 5
b1001 4
0'
1&
#305000
b1000 /
b11111111111111111111111111111111 =
b1100 <
b1100 7
b1101 6
1)
#308000
0&
#310000
0)
#315000
b1001 /
b11111111111111111111111111111111 =
b1101 <
b1101 7
1)
1&
