USART-module/design.v
module UART_module(
	input wire clk,
	input wire rst,
	input wire start,
	input wire [7:0] data_in,
	output reg tx,
	output wire busy
);

	reg [2:0] state = 3'b000;
	reg [7:0] tx_data = 8'h00;
	reg [3:0] count = 4'b0000;
	
	always @(posedge clk or posedge rst) begin
		if (rst) begin
			state <= 3'b000;
			count <= 4'b0000;
		end else begin
			case(state)
				3'b000: begin //Idle
					tx_data <= data_in;
					if (start)
						state <= 3'b001;
				end
				3'b001: begin //Start bit
					tx <= 0;
					state <= 3'b010;
				end
				3'b010: begin //Data bits
					tx <= tx_data[0];
					tx_data <= tx_data >> 1;
					count <= count + 1;
					if (count == 3)
						state <= 3'b011;
				end
				3'b011: begin //Stop bit
					tx <= 1;
					state <= 3'b000;
					count <= 4'b0000;
				end
			endcase
		end
	end
	
	assign busy = (state != 3'b000);

endmodule

USART-module/testbench.v
`include"design.v"
module UART_module_tb();

    reg clk;
    reg rst;
    reg start;
    reg [7:0] data_in;
    
    wire tx;
    wire busy;
    
    UART_module uut (
        .clk(clk),
        .rst(rst),
        .start(start),
        .data_in(data_in),
        .tx(tx),
        .busy(busy)
    );

   
    initial begin
        clk = 0;
        forever #5 clk = ~clk;
    end
    
  
    task send_uart_data(input [7:0] data);
        begin
            @(posedge clk); 
            start = 1;
            data_in = data;
            @(posedge clk);
            start = 0;
            wait (busy == 0); 
        end
    endtask
    
    
    initial begin
        rst = 1;
        start = 0;
        data_in = 8'b0;
        
    
        #20;
        rst = 0;
        
        // Test Case 1: Send a byte of data (e.g., 8'hA5)
        $display("Test Case 1: Sending 0xA5");
        send_uart_data(8'hA5);
        
        // Test Case 2: Send another byte of data (e.g., 8'h3C)
        $display("Test Case 2: Sending 0x3C");
        send_uart_data(8'h3C);
        
        // Test Case 3: Send data during busy state (should wait for completion)
        $display("Test Case 3: Sending 0xFF");
        send_uart_data(8'hFF);
        
     
        #100;
        $display("Simulation Completed");
        $finish;
    end
    
  
    initial begin
        $monitor("Time=%0t | clk=%b | rst=%b | start=%b | data_in=0x%h | tx=%b | busy=%b", 
                 $time, clk, rst, start, data_in, tx, busy);
    end

    initial begin
      $dumpfile("dump.vcd");
      $dumpvars(0);
    end

endmodule

USART-module/dump.vcd
$date
	Fri May  2 18:26:55 2025
$end
$version
	Icarus Verilog
$end
$timescale
	1s
$end
$scope module UART_module_tb $end
$var wire 1 ! tx $end
$var wire 1 " busy $end
$var reg 1 # clk $end
$var reg 8 $ data_in [7:0] $end
$var reg 1 % rst $end
$var reg 1 & start $end
$scope module uut $end
$var wire 1 # clk $end
$var wire 8 ' data_in [7:0] $end
$var wire 1 % rst $end
$var wire 1 & start $end
$var wire 1 " busy $end
$var reg 4 ( count [3:0] $end
$var reg 3 ) state [2:0] $end
$var reg 1 ! tx $end
$var reg 8 * tx_data [7:0] $end
$upscope $end
$scope task send_uart_data $end
$var reg 8 + data [7:0] $end
$upscope $end
$upscope $end
$enddefinitions $end
$comment Show the parameter values. $end
$dumpall
$end
#0
$dumpvars
bx +
b0 *
b0 )
b0 (
b0 '
0&
1%
b0 $
0#
0"
x!
$end
#5
1#
#10
0#
#15
1#
#20
0#
b10100101 +
0%
#25
1"
b1 )
b10100101 *
b10100101 $
b10100101 '
1&
1#
#30
0#
#35
b10 )
0!
0&
1#
#40
0#
#45
b1 (
b1010010 *
1!
1#
#50
0#
#55
b10 (
b101001 *
0!
1#
#60
0#
#65
b11 (
b10100 *
1!
1#
#70
0#
#75
b11 )
b100 (
b1010 *
0!
1#
#80
0#
#85
b111100 +
b0 (
0"
b0 )
1!
1#
#90
0#
#95
1"
b1 )
b111100 *
b111100 $
b111100 '
1&
1#
#100
0#
#105
b10 )
0!
0&
1#
#110
0#
#115
b1 (
b11110 *
1#
#120
0#
#125
b10 (
b1111 *
1#
#130
0#
#135
b11 (
b111 *
1!
1#
#140
0#
#145
b11 )
b100 (
b11 *
1#
#150
0#
#155
b11111111 +
b0 (
0"
b0 )
1#
#160
0#
#165
1"
b1 )
b11111111 *
b11111111 $
b11111111 '
1&
1#
#170
0#
#175
b10 )
0!
0&
1#
#180
0#
#185
b1 (
b1111111 *
1!
1#
#190
0#
#195
b10 (
b111111 *
1#
#200
0#
#205
b11 (
b11111 *
1#
#210
0#
#215
b11 )
b100 (
b1111 *
1#
#220
0#
#225
b0 (
0"
b0 )
1#
#230
0#
#235
b11111111 *
1#
